LICENSE
MANIFEST.in
README
setup.cfg
setup.py
test_extdirect.py
Flask_ExtDirect.egg-info/PKG-INFO
Flask_ExtDirect.egg-info/SOURCES.txt
Flask_ExtDirect.egg-info/dependency_links.txt
Flask_ExtDirect.egg-info/namespace_packages.txt
Flask_ExtDirect.egg-info/not-zip-safe
Flask_ExtDirect.egg-info/requires.txt
Flask_ExtDirect.egg-info/top_level.txt
docs/Makefile
docs/conf.py
docs/index.rst
docs/make.bat
docs/_themes/.gitignore
docs/_themes/LICENSE
docs/_themes/README
docs/_themes/flask_theme_support.py
docs/_themes/flask/layout.html
docs/_themes/flask/relations.html
docs/_themes/flask/theme.conf
docs/_themes/flask/static/flasky.css_t
docs/_themes/flask/static/small_flask.css
docs/_themes/flask_small/layout.html
docs/_themes/flask_small/theme.conf
docs/_themes/flask_small/static/flasky.css_t
flaskext/__init__.py
flaskext/extdirect.py