Metadata-Version: 1.0
Name: Flask-ExtDirect
Version: 0.1
Summary: Adds Ext.Direct support to Flask.
Home-page: http://github.com/paparent/Flask-ExtDirect/
Author: PA Parent
Author-email: paparent@paparent.me
License: MIT
Platform: any
Classifier: Development Status :: 3 - Alpha
Classifier: Environment :: Web Environment
Classifier: Intended Audience :: Developers
Classifier: License :: OSI Approved :: MIT License
Classifier: Operating System :: OS Independent
Classifier: Programming Language :: Python
Classifier: Topic :: Internet :: WWW/HTTP :: Dynamic Content
Classifier: Topic :: Software Development :: Libraries :: Python Modules
